nstm/__init__.py
nstm/VirtualTryOn/__init__.py
nstm/VirtualTryOn/apply_net.py
nstm/VirtualTryOn/models.py
nstm/VirtualTryOn/test.py
nstm/VirtualTryOn/utils_mask.py
nstm/VirtualTryOn/densepose/__init__.py
nstm/VirtualTryOn/densepose/config.py
nstm/VirtualTryOn/densepose/converters/__init__.py
nstm/VirtualTryOn/densepose/converters/base.py
nstm/VirtualTryOn/densepose/converters/builtin.py
nstm/VirtualTryOn/densepose/converters/chart_output_hflip.py
nstm/VirtualTryOn/densepose/converters/chart_output_to_chart_result.py
nstm/VirtualTryOn/densepose/converters/hflip.py
nstm/VirtualTryOn/densepose/converters/segm_to_mask.py
nstm/VirtualTryOn/densepose/converters/to_chart_result.py
nstm/VirtualTryOn/densepose/converters/to_mask.py
nstm/VirtualTryOn/densepose/data/__init__.py
nstm/VirtualTryOn/densepose/data/build.py
nstm/VirtualTryOn/densepose/data/combined_loader.py
nstm/VirtualTryOn/densepose/data/dataset_mapper.py
nstm/VirtualTryOn/densepose/data/image_list_dataset.py
nstm/VirtualTryOn/densepose/data/inference_based_loader.py
nstm/VirtualTryOn/densepose/data/utils.py
nstm/VirtualTryOn/densepose/data/datasets/__init__.py
nstm/VirtualTryOn/densepose/data/datasets/builtin.py
nstm/VirtualTryOn/densepose/data/datasets/chimpnsee.py
nstm/VirtualTryOn/densepose/data/datasets/coco.py
nstm/VirtualTryOn/densepose/data/datasets/dataset_type.py
nstm/VirtualTryOn/densepose/data/datasets/lvis.py
nstm/VirtualTryOn/densepose/data/meshes/__init__.py
nstm/VirtualTryOn/densepose/data/meshes/builtin.py
nstm/VirtualTryOn/densepose/data/meshes/catalog.py
nstm/VirtualTryOn/densepose/data/samplers/__init__.py
nstm/VirtualTryOn/densepose/data/samplers/densepose_base.py
nstm/VirtualTryOn/densepose/data/samplers/densepose_confidence_based.py
nstm/VirtualTryOn/densepose/data/samplers/densepose_cse_base.py
nstm/VirtualTryOn/densepose/data/samplers/densepose_cse_confidence_based.py
nstm/VirtualTryOn/densepose/data/samplers/densepose_cse_uniform.py
nstm-0.0.12.dist-info/METADATA
nstm-0.0.12.dist-info/WHEEL
nstm-0.0.12.dist-info/top_level.txt
nstm-0.0.12.dist-info/RECORD
